sphinxcontrib.direct_copy-0.0.1-py3.7-nspkg.pth
sphinxcontrib/direct-copy/__init__.py
sphinxcontrib/direct-copy/implementation.py
sphinxcontrib.direct_copy-0.0.1.dist-info/LICENSE
sphinxcontrib.direct_copy-0.0.1.dist-info/METADATA
sphinxcontrib.direct_copy-0.0.1.dist-info/WHEEL
sphinxcontrib.direct_copy-0.0.1.dist-info/namespace_packages.txt
sphinxcontrib.direct_copy-0.0.1.dist-info/top_level.txt
sphinxcontrib.direct_copy-0.0.1.dist-info/RECORD
