Metadata-Version: 2.1
Name: sphinxcontrib.direct-copy
Version: 0.0.1
Summary: Corrects relative links when generating documents  from .md to .html with commonmark
Home-page: https://github.com/cntt-n/sphinxcontrib-direct-copy
Author: Gergely Csatari
Author-email: gergely.csatari@nokia.com
License: Apache License 2.0
Keywords: helpers
Platform: UNKNOWN
Classifier: Programming Language :: Python :: 3
Classifier: Development Status :: 4 - Beta
Classifier: Topic :: Documentation
Classifier: Intended Audience :: Developers
Classifier: License :: OSI Approved :: Apache Software License
Classifier: Operating System :: POSIX
